cxwebhooks/__init__.py
cxwebhooks/requests.py
cxwebhooks/responses.py
cxwebhooks-0.0.10.dist-info/LICENSE
cxwebhooks-0.0.10.dist-info/METADATA
cxwebhooks-0.0.10.dist-info/WHEEL
cxwebhooks-0.0.10.dist-info/top_level.txt
cxwebhooks-0.0.10.dist-info/RECORD
